.coveragerc
.gitignore
.travis.yml
CHANGELOG
LICENSE
MANIFEST.in
README.md
setup.py
django_tracking2.egg-info/PKG-INFO
django_tracking2.egg-info/SOURCES.txt
django_tracking2.egg-info/dependency_links.txt
django_tracking2.egg-info/requires.txt
django_tracking2.egg-info/top_level.txt
example/manage.py
example/example/__init__.py
example/example/settings.py
example/example/urls.py
example/example/wsgi.py
example/geoip/GeoLite2-City.mmdb
example/geoip/GeoLiteCity.dat
example/geoip/LICENSE
example/templates/404.html
tracking/__init__.py
tracking/admin.py
tracking/apps.py
tracking/cache.py
tracking/handlers.py
tracking/managers.py
tracking/middleware.py
tracking/models.py
tracking/settings.py
tracking/urls.py
tracking/utils.py
tracking/views.py
tracking/migrations/0001_initial.py
tracking/migrations/0002_auto_20180918_2014.py
tracking/migrations/__init__.py
tracking/templates/tracking/dashboard.html
tracking/templates/tracking/snippets/stats.html
tracking/tests/__init__.py
tracking/tests/test_geoip.py
tracking/tests/test_managers.py
tracking/tests/test_middleware.py
tracking/tests/test_utils.py
tracking/tests/test_views.py