Metadata-Version: 1.1
Name: django-tracking2
Version: 0.5.1
Summary: django-tracking2 tracks the length of time visitors and registered users spend on your site
Home-page: https://github.com/bruth/django-tracking2
Author: Byron Ruth
Author-email: b@devel.io
License: BSD
Keywords: visitor tracking time analytics
Platform: UNKNOWN
Classifier: Development Status :: 5 - Production/Stable
Classifier: Framework :: Django
Classifier: Intended Audience :: Developers
Classifier: License :: OSI Approved :: BSD License
Classifier: Operating System :: OS Independent
Classifier: Topic :: Internet :: WWW/HTTP
Classifier: Programming Language :: Python :: 3.6
Classifier: Programming Language :: Python :: 3.7
Classifier: Programming Language :: Python :: 3.8
Classifier: Programming Language :: Python :: 3.9
Classifier: Programming Language :: Python :: 3.10
